README.rst
setup.py
remisc/README.rst
remisc/__init__.py
remisc/dxm.py
remisc/server.py
remisc/service.py
remisc.egg-info/PKG-INFO
remisc.egg-info/SOURCES.txt
remisc.egg-info/dependency_links.txt
remisc.egg-info/top_level.txt
remisc/data/__init__.py
remisc/docs/__init__.py
remisc/docs/remisc.data.html
remisc/docs/remisc.docs.html
remisc/docs/remisc.dxm.html
remisc/docs/remisc.html
remisc/docs/remisc.server.html
remisc/docs/remisc.service.html
remisc/docs/remisc.test.decorators.html
remisc/docs/remisc.test.defres.html
remisc/docs/remisc.test.html
remisc/test/__init__.py
remisc/test/decorators.py
remisc/test/defres.py