Metadata-Version: 1.1
Name: remisc
Version: 0.0.2
Summary: REST-ful microservice framework for scientific computing
Home-page: https://github.com/Tythos/remisc
Author: Brian Kirkpatrick
Author-email: code@tythos.net
License: MIT
Keywords: rest server scientific computing microservice
Platform: UNKNOWN
Classifier: Development Status :: 4 - Beta
Classifier: Environment :: Console
Classifier: Intended Audience :: Developers
Classifier: Intended Audience :: Information Technology
Classifier: Intended Audience :: Science/Research
Classifier: Intended Audience :: System Administrators
Classifier: License :: OSI Approved :: MIT License
Classifier: Operating System :: OS Independent
Classifier: Topic :: Internet :: WWW/HTTP
Classifier: Topic :: Scientific/Engineering :: Information Analysis
Classifier: Programming Language :: Python :: 2
